lwc_utils/__init__.py
lwc_utils-0.0.1.dist-info/METADATA
lwc_utils-0.0.1.dist-info/WHEEL
lwc_utils-0.0.1.dist-info/top_level.txt
lwc_utils-0.0.1.dist-info/RECORD
