Metadata-Version: 2.1
Name: lwc_utils
Version: 0.0.1
Summary: LWC Utils
Author: LWC
Requires-Python: >=3.6
Requires-Dist: numpy
